fsb795.py
fsb795-1.7.1.dist-info/METADATA
fsb795-1.7.1.dist-info/WHEEL
fsb795-1.7.1.dist-info/top_level.txt
fsb795-1.7.1.dist-info/RECORD
